agent_observability_autogpt/__init__.py
agent_observability_autogpt/plugin.py
agent_observability_autogpt-1.2.1.dist-info/licenses/LICENSE
tests/__init__.py
agent_observability_autogpt-1.2.1.dist-info/METADATA
agent_observability_autogpt-1.2.1.dist-info/WHEEL
agent_observability_autogpt-1.2.1.dist-info/top_level.txt
agent_observability_autogpt-1.2.1.dist-info/RECORD
