Metadata-Version: 2.4
Name: agent-observability-autogpt
Version: 1.2.1
Summary: AutoGPT plugin for Agent Observability - automatic logging, cost tracking, and compliance
Home-page: https://api-production-0c55.up.railway.app
Author: Agent Observability Team
Author-email: hello@agentobs.io
Project-URL: Homepage, https://api-production-0c55.up.railway.app
Project-URL: Documentation, https://api-production-0c55.up.railway.app/docs
Keywords: autogpt,agent,observability,plugin,logging,compliance,ai-agent,cost-tracking
Classifier: Development Status :: 4 - Beta
Classifier: Intended Audience :: Developers
Classifier: Topic :: Software Development :: Libraries :: Python Modules
Classifier: Topic :: System :: Monitoring
Classifier: License :: OSI Approved :: MIT License
Classifier: Programming Language :: Python :: 3
Classifier: Programming Language :: Python :: 3.10
Classifier: Programming Language :: Python :: 3.11
Classifier: Programming Language :: Python :: 3.12
Requires-Python: >=3.10
License-File: LICENSE
Requires-Dist: agent-observability>=1.1.0
Dynamic: author
Dynamic: author-email
Dynamic: classifier
Dynamic: description
Dynamic: description-content-type
Dynamic: home-page
Dynamic: keywords
Dynamic: license-file
Dynamic: project-url
Dynamic: requires-dist
Dynamic: requires-python
Dynamic: summary
